[
    {
        "id": "user1",
        "interests": [
            "data-science",
            "web-development"
        ]
    },
    {
        "id": "user2",
        "interests": [
            "python"
        ]
    },
    {
        "id": "user3",
        "interests": [
            "javascript",
            "mobile-development"
        ]
    },
    {
        "id": "user4",
        "interests": [
            "machine-learning",
            "game-development",
            "databases"
        ]
    },
    {
        "id": "user5",
        "interests": [
            "cloud-computing",
            "html"
        ]
    },
    {
        "id": "user6",
        "interests": [
            "javascript",
            "mobile-development",
            "databases"
        ]
    },
    {
        "id": "user7",
        "interests": [
            "data-science",
            "machine-learning"
        ]
    },
    {
        "id": "user8",
        "interests": [
            "mobile-development",
            "python",
            "web-development"
        ]
    },
    {
        "id": "user9",
        "interests": [
            "data-science",
            "web-development"
        ]
    },
    {
        "id": "user10",
        "interests": [
            "devops"
        ]
    },
    {
        "id": "user11",
        "interests": [
            "cloud-computing",
            "data-science"
        ]
    },
    {
        "id": "user12",
        "interests": [
            "css",
            "frontend",
            "cybersecurity"
        ]
    },
    {
        "id": "user13",
        "interests": [
            "html"
        ]
    },
    {
        "id": "user14",
        "interests": [
            "devops",
            "backend",
            "mobile-development"
        ]
    },
    {
        "id": "user15",
        "interests": [
            "javascript",
            "cloud-computing",
            "sql"
        ]
    },
    {
        "id": "user16",
        "interests": [
            "sql"
        ]
    },
    {
        "id": "user17",
        "interests": [
            "game-development",
            "html"
        ]
    },
    {
        "id": "user18",
        "interests": [
            "databases",
            "web-development"
        ]
    },
    {
        "id": "user19",
        "interests": [
            "sql",
            "web-development",
            "cloud-computing"
        ]
    },
    {
        "id": "user20",
        "interests": [
            "css"
        ]
    },
    {
        "id": "user21",
        "interests": [
            "machine-learning",
            "html"
        ]
    },
    {
        "id": "user22",
        "interests": [
            "sql",
            "backend"
        ]
    },
    {
        "id": "user23",
        "interests": [
            "python",
            "web-development"
        ]
    },
    {
        "id": "user24",
        "interests": [
            "javascript",
            "data-science"
        ]
    },
    {
        "id": "user25",
        "interests": [
            "backend",
            "frontend",
            "databases"
        ]
    },
    {
        "id": "user26",
        "interests": [
            "devops"
        ]
    },
    {
        "id": "user27",
        "interests": [
            "cybersecurity",
            "mobile-development"
        ]
    },
    {
        "id": "user28",
        "interests": [
            "sql",
            "cloud-computing",
            "javascript"
        ]
    },
    {
        "id": "user29",
        "interests": [
            "python",
            "databases"
        ]
    },
    {
        "id": "user30",
        "interests": [
            "sql"
        ]
    },
    {
        "id": "user31",
        "interests": [
            "data-science"
        ]
    },
    {
        "id": "user32",
        "interests": [
            "cloud-computing",
            "css",
            "sql"
        ]
    },
    {
        "id": "user33",
        "interests": [
            "javascript",
            "sql",
            "frontend"
        ]
    },
    {
        "id": "user34",
        "interests": [
            "data-science",
            "cybersecurity"
        ]
    },
    {
        "id": "user35",
        "interests": [
            "backend"
        ]
    },
    {
        "id": "user36",
        "interests": [
            "backend",
            "css"
        ]
    },
    {
        "id": "user37",
        "interests": [
            "frontend",
            "game-development"
        ]
    },
    {
        "id": "user38",
        "interests": [
            "backend",
            "machine-learning",
            "javascript"
        ]
    },
    {
        "id": "user39",
        "interests": [
            "web-development",
            "frontend"
        ]
    },
    {
        "id": "user40",
        "interests": [
            "html",
            "python",
            "css"
        ]
    },
    {
        "id": "user41",
        "interests": [
            "sql"
        ]
    },
    {
        "id": "user42",
        "interests": [
            "html",
            "cloud-computing",
            "python"
        ]
    },
    {
        "id": "user43",
        "interests": [
            "sql"
        ]
    },
    {
        "id": "user44",
        "interests": [
            "javascript"
        ]
    },
    {
        "id": "user45",
        "interests": [
            "mobile-development",
            "sql"
        ]
    },
    {
        "id": "user46",
        "interests": [
            "backend",
            "game-development"
        ]
    },
    {
        "id": "user47",
        "interests": [
            "game-development",
            "python"
        ]
    },
    {
        "id": "user48",
        "interests": [
            "machine-learning",
            "web-development"
        ]
    },
    {
        "id": "user49",
        "interests": [
            "html",
            "machine-learning"
        ]
    },
    {
        "id": "user50",
        "interests": [
            "python",
            "machine-learning",
            "backend"
        ]
    },
    {
        "id": "user51",
        "interests": [
            "backend"
        ]
    },
    {
        "id": "user52",
        "interests": [
            "devops",
            "css",
            "game-development"
        ]
    },
    {
        "id": "user53",
        "interests": [
            "python",
            "sql",
            "frontend"
        ]
    },
    {
        "id": "user54",
        "interests": [
            "machine-learning",
            "game-development",
            "cloud-computing"
        ]
    },
    {
        "id": "user55",
        "interests": [
            "mobile-development"
        ]
    },
    {
        "id": "user56",
        "interests": [
            "data-science",
            "backend"
        ]
    },
    {
        "id": "user57",
        "interests": [
            "devops"
        ]
    },
    {
        "id": "user58",
        "interests": [
            "cybersecurity",
            "mobile-development"
        ]
    },
    {
        "id": "user59",
        "interests": [
            "html",
            "web-development"
        ]
    },
    {
        "id": "user60",
        "interests": [
            "mobile-development"
        ]
    },
    {
        "id": "user61",
        "interests": [
            "frontend"
        ]
    },
    {
        "id": "user62",
        "interests": [
            "backend"
        ]
    },
    {
        "id": "user63",
        "interests": [
            "devops",
            "javascript"
        ]
    },
    {
        "id": "user64",
        "interests": [
            "cybersecurity",
            "css",
            "game-development"
        ]
    },
    {
        "id": "user65",
        "interests": [
            "web-development",
            "machine-learning",
            "javascript"
        ]
    },
    {
        "id": "user66",
        "interests": [
            "cybersecurity"
        ]
    },
    {
        "id": "user67",
        "interests": [
            "cloud-computing"
        ]
    },
    {
        "id": "user68",
        "interests": [
            "python"
        ]
    },
    {
        "id": "user69",
        "interests": [
            "devops",
            "css",
            "sql"
        ]
    },
    {
        "id": "user70",
        "interests": [
            "backend"
        ]
    },
    {
        "id": "user71",
        "interests": [
            "html",
            "mobile-development",
            "python"
        ]
    },
    {
        "id": "user72",
        "interests": [
            "html",
            "sql"
        ]
    },
    {
        "id": "user73",
        "interests": [
            "html",
            "cybersecurity",
            "web-development"
        ]
    },
    {
        "id": "user74",
        "interests": [
            "javascript"
        ]
    },
    {
        "id": "user75",
        "interests": [
            "machine-learning",
            "html"
        ]
    },
    {
        "id": "user76",
        "interests": [
            "machine-learning"
        ]
    },
    {
        "id": "user77",
        "interests": [
            "web-development",
            "mobile-development",
            "machine-learning"
        ]
    },
    {
        "id": "user78",
        "interests": [
            "data-science",
            "devops"
        ]
    },
    {
        "id": "user79",
        "interests": [
            "python"
        ]
    },
    {
        "id": "user80",
        "interests": [
            "machine-learning",
            "html"
        ]
    },
    {
        "id": "user81",
        "interests": [
            "cloud-computing"
        ]
    },
    {
        "id": "user82",
        "interests": [
            "cybersecurity",
            "css",
            "backend"
        ]
    },
    {
        "id": "user83",
        "interests": [
            "javascript",
            "python"
        ]
    },
    {
        "id": "user84",
        "interests": [
            "cybersecurity"
        ]
    },
    {
        "id": "user85",
        "interests": [
            "web-development",
            "css"
        ]
    },
    {
        "id": "user86",
        "interests": [
            "game-development",
            "python",
            "backend"
        ]
    },
    {
        "id": "user87",
        "interests": [
            "backend",
            "web-development"
        ]
    },
    {
        "id": "user88",
        "interests": [
            "cloud-computing",
            "backend",
            "cybersecurity"
        ]
    },
    {
        "id": "user89",
        "interests": [
            "databases",
            "cybersecurity",
            "machine-learning"
        ]
    },
    {
        "id": "user90",
        "interests": [
            "backend",
            "devops",
            "cybersecurity"
        ]
    },
    {
        "id": "user91",
        "interests": [
            "web-development"
        ]
    },
    {
        "id": "user92",
        "interests": [
            "javascript",
            "cybersecurity"
        ]
    },
    {
        "id": "user93",
        "interests": [
            "mobile-development"
        ]
    },
    {
        "id": "user94",
        "interests": [
            "css"
        ]
    },
    {
        "id": "user95",
        "interests": [
            "machine-learning"
        ]
    },
    {
        "id": "user96",
        "interests": [
            "mobile-development",
            "backend"
        ]
    },
    {
        "id": "user97",
        "interests": [
            "cloud-computing"
        ]
    },
    {
        "id": "user98",
        "interests": [
            "cybersecurity"
        ]
    },
    {
        "id": "user99",
        "interests": [
            "machine-learning",
            "html"
        ]
    },
    {
        "id": "user100",
        "interests": [
            "cybersecurity",
            "data-science"
        ]
    },
    {
        "id": "user101",
        "interests": [
            "html"
        ]
    },
    {
        "id": "user102",
        "interests": [
            "html",
            "css"
        ]
    },
    {
        "id": "user103",
        "interests": [
            "mobile-development",
            "databases"
        ]
    },
    {
        "id": "user104",
        "interests": [
            "devops",
            "data-science"
        ]
    },
    {
        "id": "user105",
        "interests": [
            "frontend",
            "web-development",
            "python"
        ]
    },
    {
        "id": "user106",
        "interests": [
            "python",
            "web-development",
            "frontend"
        ]
    },
    {
        "id": "user107",
        "interests": [
            "game-development",
            "devops",
            "sql"
        ]
    },
    {
        "id": "user108",
        "interests": [
            "mobile-development",
            "sql"
        ]
    },
    {
        "id": "user109",
        "interests": [
            "data-science",
            "html",
            "databases"
        ]
    },
    {
        "id": "user110",
        "interests": [
            "css",
            "javascript",
            "html"
        ]
    },
    {
        "id": "user111",
        "interests": [
            "web-development",
            "sql"
        ]
    },
    {
        "id": "user112",
        "interests": [
            "mobile-development",
            "css"
        ]
    },
    {
        "id": "user113",
        "interests": [
            "databases"
        ]
    },
    {
        "id": "user114",
        "interests": [
            "databases",
            "sql",
            "python"
        ]
    },
    {
        "id": "user115",
        "interests": [
            "javascript",
            "css",
            "cybersecurity"
        ]
    },
    {
        "id": "user116",
        "interests": [
            "mobile-development"
        ]
    },
    {
        "id": "user117",
        "interests": [
            "mobile-development",
            "cybersecurity",
            "css"
        ]
    },
    {
        "id": "user118",
        "interests": [
            "game-development",
            "python"
        ]
    },
    {
        "id": "user119",
        "interests": [
            "frontend",
            "sql"
        ]
    },
    {
        "id": "user120",
        "interests": [
            "python"
        ]
    },
    {
        "id": "user121",
        "interests": [
            "web-development",
            "databases"
        ]
    },
    {
        "id": "user122",
        "interests": [
            "databases"
        ]
    },
    {
        "id": "user123",
        "interests": [
            "machine-learning"
        ]
    },
    {
        "id": "user124",
        "interests": [
            "mobile-development",
            "backend"
        ]
    },
    {
        "id": "user125",
        "interests": [
            "backend",
            "cybersecurity"
        ]
    },
    {
        "id": "user126",
        "interests": [
            "web-development"
        ]
    },
    {
        "id": "user127",
        "interests": [
            "databases",
            "game-development"
        ]
    },
    {
        "id": "user128",
        "interests": [
            "game-development",
            "python"
        ]
    },
    {
        "id": "user129",
        "interests": [
            "javascript"
        ]
    },
    {
        "id": "user130",
        "interests": [
            "frontend",
            "javascript",
            "databases"
        ]
    },
    {
        "id": "user131",
        "interests": [
            "cloud-computing",
            "databases"
        ]
    },
    {
        "id": "user132",
        "interests": [
            "python",
            "game-development",
            "mobile-development"
        ]
    },
    {
        "id": "user133",
        "interests": [
            "game-development"
        ]
    },
    {
        "id": "user134",
        "interests": [
            "databases",
            "data-science",
            "mobile-development"
        ]
    },
    {
        "id": "user135",
        "interests": [
            "frontend",
            "sql"
        ]
    },
    {
        "id": "user136",
        "interests": [
            "cloud-computing",
            "machine-learning"
        ]
    },
    {
        "id": "user137",
        "interests": [
            "python"
        ]
    },
    {
        "id": "user138",
        "interests": [
            "devops",
            "javascript",
            "databases"
        ]
    },
    {
        "id": "user139",
        "interests": [
            "databases"
        ]
    },
    {
        "id": "user140",
        "interests": [
            "devops",
            "python",
            "frontend"
        ]
    },
    {
        "id": "user141",
        "interests": [
            "game-development"
        ]
    },
    {
        "id": "user142",
        "interests": [
            "python",
            "frontend",
            "html"
        ]
    },
    {
        "id": "user143",
        "interests": [
            "javascript"
        ]
    },
    {
        "id": "user144",
        "interests": [
            "sql"
        ]
    },
    {
        "id": "user145",
        "interests": [
            "databases",
            "machine-learning"
        ]
    },
    {
        "id": "user146",
        "interests": [
            "sql",
            "databases"
        ]
    },
    {
        "id": "user147",
        "interests": [
            "javascript",
            "cloud-computing",
            "databases"
        ]
    },
    {
        "id": "user148",
        "interests": [
            "game-development",
            "cybersecurity",
            "sql"
        ]
    },
    {
        "id": "user149",
        "interests": [
            "cybersecurity"
        ]
    },
    {
        "id": "user150",
        "interests": [
            "css"
        ]
    },
    {
        "id": "user151",
        "interests": [
            "css",
            "html"
        ]
    },
    {
        "id": "user152",
        "interests": [
            "backend"
        ]
    },
    {
        "id": "user153",
        "interests": [
            "mobile-development",
            "web-development"
        ]
    },
    {
        "id": "user154",
        "interests": [
            "python",
            "databases",
            "mobile-development"
        ]
    },
    {
        "id": "user155",
        "interests": [
            "backend"
        ]
    },
    {
        "id": "user156",
        "interests": [
            "cybersecurity"
        ]
    },
    {
        "id": "user157",
        "interests": [
            "game-development",
            "devops"
        ]
    },
    {
        "id": "user158",
        "interests": [
            "frontend"
        ]
    },
    {
        "id": "user159",
        "interests": [
            "machine-learning",
            "databases"
        ]
    },
    {
        "id": "user160",
        "interests": [
            "web-development"
        ]
    },
    {
        "id": "user161",
        "interests": [
            "backend",
            "data-science"
        ]
    },
    {
        "id": "user162",
        "interests": [
            "data-science"
        ]
    },
    {
        "id": "user163",
        "interests": [
            "html"
        ]
    },
    {
        "id": "user164",
        "interests": [
            "data-science",
            "databases",
            "html"
        ]
    },
    {
        "id": "user165",
        "interests": [
            "frontend",
            "machine-learning",
            "css"
        ]
    },
    {
        "id": "user166",
        "interests": [
            "web-development",
            "databases"
        ]
    },
    {
        "id": "user167",
        "interests": [
            "css",
            "frontend",
            "devops"
        ]
    },
    {
        "id": "user168",
        "interests": [
            "web-development",
            "cloud-computing",
            "python"
        ]
    },
    {
        "id": "user169",
        "interests": [
            "data-science",
            "web-development",
            "sql"
        ]
    },
    {
        "id": "user170",
        "interests": [
            "cloud-computing",
            "devops"
        ]
    },
    {
        "id": "user171",
        "interests": [
            "game-development",
            "css"
        ]
    },
    {
        "id": "user172",
        "interests": [
            "backend"
        ]
    },
    {
        "id": "user173",
        "interests": [
            "data-science"
        ]
    },
    {
        "id": "user174",
        "interests": [
            "game-development",
            "html",
            "data-science"
        ]
    },
    {
        "id": "user175",
        "interests": [
            "data-science"
        ]
    },
    {
        "id": "user176",
        "interests": [
            "javascript",
            "backend"
        ]
    },
    {
        "id": "user177",
        "interests": [
            "python",
            "css",
            "mobile-development"
        ]
    },
    {
        "id": "user178",
        "interests": [
            "javascript"
        ]
    },
    {
        "id": "user179",
        "interests": [
            "backend",
            "html"
        ]
    },
    {
        "id": "user180",
        "interests": [
            "data-science",
            "css"
        ]
    },
    {
        "id": "user181",
        "interests": [
            "data-science",
            "html",
            "backend"
        ]
    },
    {
        "id": "user182",
        "interests": [
            "html"
        ]
    },
    {
        "id": "user183",
        "interests": [
            "css",
            "cybersecurity"
        ]
    },
    {
        "id": "user184",
        "interests": [
            "cybersecurity",
            "html"
        ]
    },
    {
        "id": "user185",
        "interests": [
            "cybersecurity"
        ]
    },
    {
        "id": "user186",
        "interests": [
            "html"
        ]
    },
    {
        "id": "user187",
        "interests": [
            "sql",
            "game-development"
        ]
    },
    {
        "id": "user188",
        "interests": [
            "mobile-development"
        ]
    },
    {
        "id": "user189",
        "interests": [
            "javascript",
            "html",
            "sql"
        ]
    },
    {
        "id": "user190",
        "interests": [
            "css"
        ]
    },
    {
        "id": "user191",
        "interests": [
            "cybersecurity"
        ]
    },
    {
        "id": "user192",
        "interests": [
            "html"
        ]
    },
    {
        "id": "user193",
        "interests": [
            "backend"
        ]
    },
    {
        "id": "user194",
        "interests": [
            "cloud-computing",
            "html",
            "mobile-development"
        ]
    },
    {
        "id": "user195",
        "interests": [
            "machine-learning",
            "javascript"
        ]
    },
    {
        "id": "user196",
        "interests": [
            "data-science"
        ]
    },
    {
        "id": "user197",
        "interests": [
            "data-science"
        ]
    },
    {
        "id": "user198",
        "interests": [
            "mobile-development",
            "html"
        ]
    },
    {
        "id": "user199",
        "interests": [
            "javascript",
            "game-development",
            "databases"
        ]
    },
    {
        "id": "user200",
        "interests": [
            "frontend"
        ]
    },
    {
        "id": "user201"
    }
]